{
  "totalUrls": 31,
  "success": 31,
  "errors": [],
  "pages": [
    {
      "route": "/painel",
      "status": 200,
      "title": "MX Gestão Preditiva",
      "hasErrorBoundary": false,
      "screenshot": "/Users/pedroguilherme/PROJETOS/MX GESTAO PREDITIVA/.temp/audit_screenshots/_painel.png",
      "pageErrors": [],
      "consoleErrors": [],
      "networkErrors": [
        "https://autogestao.vercel.app/assets/trending-up-D2fZf5Tm.js: net::ERR_ABORTED",
        "https://autogestao.vercel.app/assets/award-CXwrAAgT.js: net::ERR_ABORTED",
        "https://autogestao.vercel.app/assets/chevron-right-COQzs4zi.js: net::ERR_ABORTED",
        "https://fbhcmzzgwjdgkctlfvbo.supabase.co/rest/v1/notifications?select=*&order=sent_at.desc&limit=50: net::ERR_ABORTED",
        "https://autogestao.vercel.app/assets/PainelConsultor-DwdGn_LV.js: net::ERR_ABORTED"
      ]
    },
    {
      "route": "/lojas",
      "status": 200,
      "title": "MX Gestão Preditiva",
      "hasErrorBoundary": false,
      "screenshot": "/Users/pedroguilherme/PROJETOS/MX GESTAO PREDITIVA/.temp/audit_screenshots/_lojas.png",
      "pageErrors": [],
      "consoleErrors": [],
      "networkErrors": []
    },
    {
      "route": "/loja",
      "status": 200,
      "title": "MX Gestão Preditiva",
      "hasErrorBoundary": false,
      "screenshot": "/Users/pedroguilherme/PROJETOS/MX GESTAO PREDITIVA/.temp/audit_screenshots/_loja.png",
      "pageErrors": [],
      "consoleErrors": [],
      "networkErrors": []
    },
    {
      "route": "/agenda",
      "status": 200,
      "title": "MX Gestão Preditiva",
      "hasErrorBoundary": false,
      "screenshot": "/Users/pedroguilherme/PROJETOS/MX GESTAO PREDITIVA/.temp/audit_screenshots/_agenda.png",
      "pageErrors": [],
      "consoleErrors": [],
      "networkErrors": []
    },
    {
      "route": "/leadops",
      "status": 200,
      "title": "MX Gestão Preditiva",
      "hasErrorBoundary": false,
      "screenshot": "/Users/pedroguilherme/PROJETOS/MX GESTAO PREDITIVA/.temp/audit_screenshots/_leadops.png",
      "pageErrors": [],
      "consoleErrors": [],
      "networkErrors": []
    },
    {
      "route": "/leads",
      "status": 200,
      "title": "MX Gestão Preditiva",
      "hasErrorBoundary": false,
      "screenshot": "/Users/pedroguilherme/PROJETOS/MX GESTAO PREDITIVA/.temp/audit_screenshots/_leads.png",
      "pageErrors": [],
      "consoleErrors": [],
      "networkErrors": []
    },
    {
      "route": "/equipe",
      "status": 200,
      "title": "MX Gestão Preditiva",
      "hasErrorBoundary": false,
      "screenshot": "/Users/pedroguilherme/PROJETOS/MX GESTAO PREDITIVA/.temp/audit_screenshots/_equipe.png",
      "pageErrors": [],
      "consoleErrors": [],
      "networkErrors": []
    },
    {
      "route": "/tarefas",
      "status": 200,
      "title": "MX Gestão Preditiva",
      "hasErrorBoundary": false,
      "screenshot": "/Users/pedroguilherme/PROJETOS/MX GESTAO PREDITIVA/.temp/audit_screenshots/_tarefas.png",
      "pageErrors": [],
      "consoleErrors": [],
      "networkErrors": []
    },
    {
      "route": "/metas",
      "status": 200,
      "title": "MX Gestão Preditiva",
      "hasErrorBoundary": false,
      "screenshot": "/Users/pedroguilherme/PROJETOS/MX GESTAO PREDITIVA/.temp/audit_screenshots/_metas.png",
      "pageErrors": [],
      "consoleErrors": [],
      "networkErrors": []
    },
    {
      "route": "/funil",
      "status": 200,
      "title": "MX Gestão Preditiva",
      "hasErrorBoundary": false,
      "screenshot": "/Users/pedroguilherme/PROJETOS/MX GESTAO PREDITIVA/.temp/audit_screenshots/_funil.png",
      "pageErrors": [],
      "consoleErrors": [],
      "networkErrors": []
    },
    {
      "route": "/checkin",
      "status": 200,
      "title": "MX Gestão Preditiva",
      "hasErrorBoundary": false,
      "screenshot": "/Users/pedroguilherme/PROJETOS/MX GESTAO PREDITIVA/.temp/audit_screenshots/_checkin.png",
      "pageErrors": [],
      "consoleErrors": [],
      "networkErrors": []
    },
    {
      "route": "/historico",
      "status": 200,
      "title": "MX Gestão Preditiva",
      "hasErrorBoundary": false,
      "screenshot": "/Users/pedroguilherme/PROJETOS/MX GESTAO PREDITIVA/.temp/audit_screenshots/_historico.png",
      "pageErrors": [],
      "consoleErrors": [],
      "networkErrors": []
    },
    {
      "route": "/ranking",
      "status": 200,
      "title": "MX Gestão Preditiva",
      "hasErrorBoundary": false,
      "screenshot": "/Users/pedroguilherme/PROJETOS/MX GESTAO PREDITIVA/.temp/audit_screenshots/_ranking.png",
      "pageErrors": [],
      "consoleErrors": [],
      "networkErrors": []
    },
    {
      "route": "/relatorio-matinal",
      "status": 200,
      "title": "MX Gestão Preditiva",
      "hasErrorBoundary": false,
      "screenshot": "/Users/pedroguilherme/PROJETOS/MX GESTAO PREDITIVA/.temp/audit_screenshots/_relatorio_matinal.png",
      "pageErrors": [],
      "consoleErrors": [],
      "networkErrors": []
    },
    {
      "route": "/financeiro",
      "status": 200,
      "title": "MX Gestão Preditiva",
      "hasErrorBoundary": false,
      "screenshot": "/Users/pedroguilherme/PROJETOS/MX GESTAO PREDITIVA/.temp/audit_screenshots/_financeiro.png",
      "pageErrors": [],
      "consoleErrors": [],
      "networkErrors": []
    },
    {
      "route": "/inventory",
      "status": 200,
      "title": "MX Gestão Preditiva",
      "hasErrorBoundary": false,
      "screenshot": "/Users/pedroguilherme/PROJETOS/MX GESTAO PREDITIVA/.temp/audit_screenshots/_inventory.png",
      "pageErrors": [],
      "consoleErrors": [],
      "networkErrors": []
    },
    {
      "route": "/configuracoes/comissoes",
      "status": 200,
      "title": "MX Gestão Preditiva",
      "hasErrorBoundary": false,
      "screenshot": "/Users/pedroguilherme/PROJETOS/MX GESTAO PREDITIVA/.temp/audit_screenshots/_configuracoes_comissoes.png",
      "pageErrors": [],
      "consoleErrors": [],
      "networkErrors": []
    },
    {
      "route": "/treinamentos",
      "status": 200,
      "title": "MX Gestão Preditiva",
      "hasErrorBoundary": false,
      "screenshot": "/Users/pedroguilherme/PROJETOS/MX GESTAO PREDITIVA/.temp/audit_screenshots/_treinamentos.png",
      "pageErrors": [],
      "consoleErrors": [],
      "networkErrors": []
    },
    {
      "route": "/communication",
      "status": 200,
      "title": "MX Gestão Preditiva",
      "hasErrorBoundary": false,
      "screenshot": "/Users/pedroguilherme/PROJETOS/MX GESTAO PREDITIVA/.temp/audit_screenshots/_communication.png",
      "pageErrors": [],
      "consoleErrors": [],
      "networkErrors": []
    },
    {
      "route": "/ia-diagnostics",
      "status": 200,
      "title": "MX Gestão Preditiva",
      "hasErrorBoundary": false,
      "screenshot": "/Users/pedroguilherme/PROJETOS/MX GESTAO PREDITIVA/.temp/audit_screenshots/_ia_diagnostics.png",
      "pageErrors": [],
      "consoleErrors": [],
      "networkErrors": []
    },
    {
      "route": "/relatorios/performance-vendas",
      "status": 200,
      "title": "MX Gestão Preditiva",
      "hasErrorBoundary": false,
      "screenshot": "/Users/pedroguilherme/PROJETOS/MX GESTAO PREDITIVA/.temp/audit_screenshots/_relatorios_performance_vendas.png",
      "pageErrors": [],
      "consoleErrors": [],
      "networkErrors": []
    },
    {
      "route": "/relatorios/performance-vendedores",
      "status": 200,
      "title": "MX Gestão Preditiva",
      "hasErrorBoundary": false,
      "screenshot": "/Users/pedroguilherme/PROJETOS/MX GESTAO PREDITIVA/.temp/audit_screenshots/_relatorios_performance_vendedores.png",
      "pageErrors": [],
      "consoleErrors": [],
      "networkErrors": []
    },
    {
      "route": "/relatorios/vendas-cruzados",
      "status": 200,
      "title": "MX Gestão Preditiva",
      "hasErrorBoundary": false,
      "screenshot": "/Users/pedroguilherme/PROJETOS/MX GESTAO PREDITIVA/.temp/audit_screenshots/_relatorios_vendas_cruzados.png",
      "pageErrors": [],
      "consoleErrors": [],
      "networkErrors": []
    },
    {
      "route": "/reports/stock",
      "status": 200,
      "title": "MX Gestão Preditiva",
      "hasErrorBoundary": false,
      "screenshot": "/Users/pedroguilherme/PROJETOS/MX GESTAO PREDITIVA/.temp/audit_screenshots/_reports_stock.png",
      "pageErrors": [],
      "consoleErrors": [],
      "networkErrors": []
    },
    {
      "route": "/activities",
      "status": 200,
      "title": "MX Gestão Preditiva",
      "hasErrorBoundary": false,
      "screenshot": "/Users/pedroguilherme/PROJETOS/MX GESTAO PREDITIVA/.temp/audit_screenshots/_activities.png",
      "pageErrors": [],
      "consoleErrors": [],
      "networkErrors": []
    },
    {
      "route": "/gamification",
      "status": 200,
      "title": "MX Gestão Preditiva",
      "hasErrorBoundary": false,
      "screenshot": "/Users/pedroguilherme/PROJETOS/MX GESTAO PREDITIVA/.temp/audit_screenshots/_gamification.png",
      "pageErrors": [],
      "consoleErrors": [],
      "networkErrors": []
    },
    {
      "route": "/feedback",
      "status": 200,
      "title": "MX Gestão Preditiva",
      "hasErrorBoundary": false,
      "screenshot": "/Users/pedroguilherme/PROJETOS/MX GESTAO PREDITIVA/.temp/audit_screenshots/_feedback.png",
      "pageErrors": [],
      "consoleErrors": [],
      "networkErrors": []
    },
    {
      "route": "/notificacoes",
      "status": 200,
      "title": "MX Gestão Preditiva",
      "hasErrorBoundary": false,
      "screenshot": "/Users/pedroguilherme/PROJETOS/MX GESTAO PREDITIVA/.temp/audit_screenshots/_notificacoes.png",
      "pageErrors": [],
      "consoleErrors": [],
      "networkErrors": []
    },
    {
      "route": "/produtos",
      "status": 200,
      "title": "MX Gestão Preditiva",
      "hasErrorBoundary": false,
      "screenshot": "/Users/pedroguilherme/PROJETOS/MX GESTAO PREDITIVA/.temp/audit_screenshots/_produtos.png",
      "pageErrors": [],
      "consoleErrors": [],
      "networkErrors": []
    },
    {
      "route": "/configuracoes",
      "status": 200,
      "title": "MX Gestão Preditiva",
      "hasErrorBoundary": false,
      "screenshot": "/Users/pedroguilherme/PROJETOS/MX GESTAO PREDITIVA/.temp/audit_screenshots/_configuracoes.png",
      "pageErrors": [],
      "consoleErrors": [],
      "networkErrors": []
    },
    {
      "route": "/perfil",
      "status": 200,
      "title": "MX Gestão Preditiva",
      "hasErrorBoundary": false,
      "screenshot": "/Users/pedroguilherme/PROJETOS/MX GESTAO PREDITIVA/.temp/audit_screenshots/_perfil.png",
      "pageErrors": [],
      "consoleErrors": [],
      "networkErrors": []
    }
  ]
}